{"title":"An Antarctic Tour of the Tidyverse","markdown":{"yaml":{"title":"An Antarctic Tour of the Tidyverse","date":"2020-08-31","slug":"tour-of-the-tidyverse","alias":["/talk/2020-08-31-tour-of-the-tidyverse/"],"categories":["R","Education","Tutorial"],"tags":["R-Ladies","tidyverse","R"],"image":"featured.jpg","subtitle":"An introductory tidyverse tutorial created and presented for R-Ladies Chicago","summary":"An introductory tidyverse tutorial created and presented for [R-Ladies Chicago](https://rladieschicago.org/)","featured":"yes","slides":"","projects":[],"links":[{"icon":"images","icon_pack":"fas","name":"slides","url":"https://slides.silviacanelon.com/tour-of-the-tidyverse"},{"icon":"play-circle","icon_pack":"fas","name":"video","url":"https://youtu.be/m_ZoMmAIx-o"},{"icon":"github","icon_pack":"fab","name":"materials","url":"https://github.com/spcanelon/tour-of-the-tidyverse#an-antarctic-tour-of-the-tidyverse"}]},"headingText":"Description","containsRefs":false,"markdown":"\n\nLearn how to explore and manipulate data in R with packages from the Tidyverse. We'll introduce the [eight core packages that make up the Tidyverse](https://www.tidyverse.org/packages/#core-tidyverse) and use at least one function from each package while exploring a dataset on the migration of penguins.\n<br><br>\n\n## Slides\n\n```{r setup, include=FALSE, eval=TRUE}\nlibrary(xaringanExtra)\n```\n\n```{r echo=FALSE, eval=TRUE}\nxaringanExtra::embed_xaringan(\n  url = \"https://spcanelon.github.io/tour-of-the-tidyverse\",\n  ratio = \"16:9\")\n```\n"},"formats":{"html":{"execute":{"fig-width":7,"fig-height":5,"fig-format":"retina","fig-dpi":96,"df-print":"default","error":false,"eval":true,"cache":null,"freeze":true,"echo":true,"output":true,"warning":true,"include":true,"keep-md":false,"keep-ipynb":false,"ipynb":null,"enabled":null,"daemon":null,"daemon-restart":false,"debug":false,"ipynb-filters":[],"engine":"knitr"},"render":{"keep-tex":false,"keep-yaml":false,"keep-source":false,"keep-hidden":false,"prefer-html":false,"output-divs":true,"output-ext":"html","fig-align":"default","fig-pos":null,"fig-env":null,"code-fold":"none","code-overflow":"scroll","code-link":false,"code-line-numbers":false,"code-tools":false,"tbl-colwidths":"auto","merge-includes":true,"latex-auto-mk":true,"latex-auto-install":true,"latex-clean":true,"latex-max-runs":10,"latex-makeindex":"makeindex","latex-makeindex-opts":[],"latex-tlmgr-opts":[],"latex-input-paths":[],"latex-output-dir":null,"link-external-icon":false,"link-external-newwindow":false,"self-contained-math":false,"format-resources":[]},"pandoc":{"standalone":true,"wrap":"none","default-image-extension":"png","to":"html","css":["../../assets/styles.css"],"highlight-style":"assets/silvia-syntax.theme","output-file":"index.html"},"language":{},"metadata":{"lang":"en","fig-responsive":true,"quarto-version":"1.0.38","theme":["litera","../../assets/silvia-theme.scss"],"backgroundcolor":"#fffbf2","title-block-banner":false,"title":"An Antarctic Tour of the Tidyverse","date":"2020-08-31","slug":"tour-of-the-tidyverse","alias":["/talk/2020-08-31-tour-of-the-tidyverse/"],"categories":["R","Education","Tutorial"],"tags":["R-Ladies","tidyverse","R"],"image":"featured.jpg","subtitle":"An introductory tidyverse tutorial created and presented for R-Ladies Chicago","summary":"An introductory tidyverse tutorial created and presented for [R-Ladies Chicago](https://rladieschicago.org/)","featured":"yes","slides":"","projects":[],"links":[{"icon":"images","icon_pack":"fas","name":"slides","url":"https://slides.silviacanelon.com/tour-of-the-tidyverse"},{"icon":"play-circle","icon_pack":"fas","name":"video","url":"https://youtu.be/m_ZoMmAIx-o"},{"icon":"github","icon_pack":"fab","name":"materials","url":"https://github.com/spcanelon/tour-of-the-tidyverse#an-antarctic-tour-of-the-tidyverse"}]},"extensions":{"book":{"multiFile":true}}}}}